index.py
lib/fact.py
python_package_test-0.0.14.dist-info/LICENSE
python_package_test-0.0.14.dist-info/METADATA
python_package_test-0.0.14.dist-info/WHEEL
python_package_test-0.0.14.dist-info/entry_points.txt
python_package_test-0.0.14.dist-info/top_level.txt
python_package_test-0.0.14.dist-info/RECORD
